pytest_instrument/__init__.py
pytest_instrument/hooks.py
pytest_instrument/logging_helpers.py
pytest_instrument/plugin.py
pytest_instrument-0.3.1.dist-info/DESCRIPTION.rst
pytest_instrument-0.3.1.dist-info/METADATA
pytest_instrument-0.3.1.dist-info/RECORD
pytest_instrument-0.3.1.dist-info/WHEEL
pytest_instrument-0.3.1.dist-info/entry_points.txt
pytest_instrument-0.3.1.dist-info/metadata.json
pytest_instrument-0.3.1.dist-info/top_level.txt
