Metadata-Version: 2.0
Name: pytest-instrument
Version: 0.3.1
Summary: pytest plugin to instrument tests
Home-page: https://github.com/j19sch/pytest-instrument
Author: Joep Schuurkes
Author-email: j19sch@gmail.com
Maintainer: Joep Schuurkes
Maintainer-email: j19sch@gmail.com
License: MIT
Platform: UNKNOWN
Classifier: Development Status :: 5 - Production/Stable
Classifier: Framework :: Pytest
Classifier: Intended Audience :: Developers
Classifier: Topic :: Software Development :: Testing
Classifier: Programming Language :: Python
Classifier: Programming Language :: Python :: 3.6
Classifier: Programming Language :: Python :: 3.7
Classifier: Programming Language :: Python :: 3.8
Classifier: Programming Language :: Python :: Implementation :: CPython
Classifier: Operating System :: OS Independent
Classifier: License :: OSI Approved :: MIT License
Requires-Python: >=3.6
Requires-Dist: pytest (>=5.1.0)
Requires-Dist: python-json-logger (>=0.1.11)
